spark_sql_generator/__init__.py
spark_sql_generator/helper.py
spark_sql_generator-0.0.2.dist-info/METADATA
spark_sql_generator-0.0.2.dist-info/WHEEL
spark_sql_generator-0.0.2.dist-info/licenses/LICENSE
spark_sql_generator-0.0.2.dist-info/RECORD
