Metadata-Version: 2.4
Name: spark_sql_generator
Version: 0.0.2
Summary: This module generates SQL DDL statements for schema modifications in database tables, with special support for complex nested data structures.
Project-URL: Homepage, https://github.com/dinesh-kumar-g-31/spark-sql-generator.git
Project-URL: Issues, https://github.com/dinesh-kumar-g-31/spark-sql-generator/issues
Author-email: DINESH KUMAR G <dineshkumarbe1331@gmail.com>
License-Expression: MIT
License-File: LICENSE
Keywords: ARRAY_PROCESSING,CODE_GENERATION,DDL,FIELD_ORDERING,NESTED_STRUCTURES,PATH_HANDLING,SCHEMA,SPARK,SQL,STRUCT_FORMATTING
Classifier: Operating System :: OS Independent
Classifier: Programming Language :: Python :: 3
Requires-Python: >=3.9
Requires-Dist: sqlglot
